releasy/__init__.py
releasy/contributor.py
releasy/miner_base.py
releasy/miner_base_release.py
releasy/miner_commit.py
releasy/miner_contributor.py
releasy/miner_release.py
releasy/miner_semantic.py
releasy/project.py
releasy/release.py
releasy/repository.py
releasy/repository_git.py
releasy/semantic.py
releasy_lib-4.2.3.dist-info/LICENSE.txt
releasy_lib-4.2.3.dist-info/METADATA
releasy_lib-4.2.3.dist-info/WHEEL
releasy_lib-4.2.3.dist-info/RECORD
